ssa/__init__.py
ssa/ssa.py
ssa/utils.py
singular_specturm_analysis-0.0.1.1.dist-info/LICENSE
singular_specturm_analysis-0.0.1.1.dist-info/METADATA
singular_specturm_analysis-0.0.1.1.dist-info/WHEEL
singular_specturm_analysis-0.0.1.1.dist-info/top_level.txt
singular_specturm_analysis-0.0.1.1.dist-info/RECORD
